devopsdriver/__init__.py
devopsdriver/dataobject.py
devopsdriver/manage_settings.py
devopsdriver/sendmail.py
devopsdriver/settings.py
devopsdriver/template.py
devopsdriver/azdo/__init__.py
devopsdriver/azdo/azureobject.py
devopsdriver/azdo/clients.py
devopsdriver/azdo/timestamp.py
devopsdriver/azdo/builds/__init__.py
devopsdriver/azdo/builds/build.py
devopsdriver/azdo/builds/client.py
devopsdriver/azdo/pipeline/__init__.py
devopsdriver/azdo/pipeline/client.py
devopsdriver/azdo/pipeline/log.py
devopsdriver/azdo/pipeline/pipeline.py
devopsdriver/azdo/pipeline/run.py
devopsdriver/azdo/workitem/__init__.py
devopsdriver/azdo/workitem/client.py
devopsdriver/azdo/workitem/wiql.py
devopsdriver/github/__init__.py
devopsdriver/github/client.py
devopsdriver/templates/manage_settings.txt.mako
devopsdriver-0.1.52.dist-info/licenses/LICENSE
devopsdriver-0.1.52.dist-info/METADATA
devopsdriver-0.1.52.dist-info/WHEEL
devopsdriver-0.1.52.dist-info/entry_points.txt
devopsdriver-0.1.52.dist-info/top_level.txt
devopsdriver-0.1.52.dist-info/RECORD
