Metadata-Version: 2.4
Name: devopsdriver
Version: 0.1.52
Summary: DevOps tools
Author-email: Marc Page <marcallenpage@gmail.com>
License: This is free and unencumbered software released into the public domain.
Project-URL: Homepage, https://github.com/marcpage/devops-driver
Project-URL: Documentation, https://github.com/marcpage/devops-driver
Project-URL: Repository, https://github.com/marcpage/devops-driver.git
Project-URL: Issues, https://github.com/marcpage/devops-driver/issues
Project-URL: Changelog, https://github.com/marcpage/devops-driver/releases
Keywords: azure,devops,jira,confluence,email,pipelines,tools,github
Classifier: Development Status :: 1 - Planning
Classifier: Environment :: Console
Classifier: Intended Audience :: Developers
Classifier: Programming Language :: Python
Classifier: Programming Language :: Python :: 3
Classifier: License :: OSI Approved :: The Unlicense (Unlicense)
Classifier: Programming Language :: Python :: 3.10
Classifier: Topic :: Utilities
Classifier: Topic :: Software Development
Requires-Python: >=3.10
License-File: LICENSE
Requires-Dist: PyYAML==6.0.3
Requires-Dist: keyring==25.6.0
Requires-Dist: setuptools==80.9.0
Requires-Dist: azure-devops==7.1.0b4
Requires-Dist: Mako==1.3.10
Requires-Dist: PyGithub==2.8.1
Provides-Extra: dev
Requires-Dist: black>=24.3.0; extra == "dev"
Requires-Dist: pylint>=3.1.0; extra == "dev"
Provides-Extra: test
Requires-Dist: pytest>=8.1.1; extra == "test"
Requires-Dist: coverage>=7.4.4; extra == "test"
Provides-Extra: doc
Dynamic: license-file
